LICENSE
NOTICE
src/command.py
cyclonedx_conan-0.4.1.dist-info/LICENSE
cyclonedx_conan-0.4.1.dist-info/METADATA
cyclonedx_conan-0.4.1.dist-info/WHEEL
cyclonedx_conan-0.4.1.dist-info/entry_points.txt
cyclonedx_conan-0.4.1.dist-info/RECORD
