Metadata-Version: 2.1
Name: cyclonedx-conan
Version: 0.4.1
Summary: Creates CycloneDX Software Bill of Materials (SBOM) documents for C/C++ projects using Conan
Home-page: https://github.com/CycloneDX/cyclonedx-conan#readme
License: Apache-2.0
Author: Patrick Dwyer
Author-email: patrick.dwyer@owasp.org
Maintainer: Patrick Dwyer
Maintainer-email: patrick.dwyer@owasp.org
Requires-Python: >=3.6,<4.0
Classifier: License :: OSI Approved :: Apache Software License
Classifier: Programming Language :: Python :: 3
Classifier: Programming Language :: Python :: 3.6
Classifier: Programming Language :: Python :: 3.7
Classifier: Programming Language :: Python :: 3.8
Classifier: Programming Language :: Python :: 3.9
Classifier: Programming Language :: Python :: 3.10
Classifier: Programming Language :: Python :: 3.11
Requires-Dist: conan (>=1.41.0,<2.0.0)
Requires-Dist: packageurl-python (>=0.9.6,<0.10.0)
Project-URL: Repository, https://github.com/CycloneDX/cyclonedx-conan
